odoo/addons/sale_helm/LICENSE
odoo/addons/sale_helm/README.rst
odoo/addons/sale_helm/__init__.py
odoo/addons/sale_helm/__manifest__.py
odoo/addons/sale_helm/data/data.xml
odoo/addons/sale_helm/demo/demo.xml
odoo/addons/sale_helm/images/screen.png
odoo/addons/sale_helm/models/__init__.py
odoo/addons/sale_helm/models/helm_release.py
odoo/addons/sale_helm/models/sale_order.py
odoo/addons/sale_helm/models/sale_order_line.py
odoo/addons/sale_helm/static/description/icon.png
odoo/addons/sale_helm/static/description/index.html
odoo/addons/sale_helm/tests/TEST_INSTRUCTIONS.rst
odoo/addons/sale_helm/views/sale_order_views.xml
odoo_addon_sale_helm-18.0.1.0.0.dist-info/METADATA
odoo_addon_sale_helm-18.0.1.0.0.dist-info/WHEEL
odoo_addon_sale_helm-18.0.1.0.0.dist-info/top_level.txt
odoo_addon_sale_helm-18.0.1.0.0.dist-info/RECORD
